ProjectScope/ProjectScopeViewer.py
ProjectScope/__init__.py
ProjectScope/__main__.py
ProjectScope/db_upgrades.py
ProjectScope/version_info.txt
ProjectScope-0.0.12.dist-info/LICENSE
ProjectScope-0.0.12.dist-info/METADATA
ProjectScope-0.0.12.dist-info/WHEEL
ProjectScope-0.0.12.dist-info/top_level.txt
ProjectScope-0.0.12.dist-info/RECORD
