Metadata-Version: 2.1
Name: ProjectScope
Version: 0.0.12
Summary: A small project management tool
Home-page: https://bitbucket.org/CoreyBird/projectscope/src/master/
Author: Corey Bird
Author-email: birdcorey@gmail.com
License: MIT
Download-URL: https://bitbucket.org/CoreyBird/projectscope/src/master/dist/ProjectScope-0.0.12.tar.gz
Platform: UNKNOWN
Classifier: Programming Language :: Python :: 3
Classifier: License :: OSI Approved :: MIT License
Classifier: Operating System :: OS Independent
Requires-Python: >=3.7
Requires-Dist: wxPython
Requires-Dist: Panda3D
